components/__init__.py
components/envelopegrating/__init__.py
components/envelopegrating/classic/envelope_grating@2x.png
components/envelopegrating/classic/envelopegrating.png
components/envelopegrating/dark/envelopegrating.png
components/envelopegrating/dark/envelopegrating@2x.png
components/envelopegrating/light/envelopegrating.png
components/envelopegrating/light/envelopegrating@2x.png
components/noise/__init__.py
components/noise/classic/noise.png
components/noise/classic/noise@2x.png
components/noise/dark/noise.png
components/noise/dark/noise@2x.png
components/noise/light/noise.png
components/noise/light/noise@2x.png
components/radial/__init__.py
components/radial/classic/radial.png
components/radial/classic/radial@2x.png
components/radial/dark/radial.png
components/radial/dark/radial@2x.png
components/radial/light/radial.png
components/radial/light/radial@2x.png
docs_src/conf.py
docs_src/favicon.png
docs_src/themes/psychopy_plugin/static/Nottingham Supported.png
docs_src/themes/psychopy_plugin/static/Psychopy Plugin Header Large.png
docs_src/themes/psychopy_plugin/static/Psychopy Plugin Header Small.png
psychopy_visionscience/__init__.py
psychopy_visionscience/noise.py
psychopy_visionscience/radial.py
psychopy_visionscience/secondorder.py
psychopy_visionscience/components/__init__.py
psychopy_visionscience/components/envelopegrating/__init__.py
psychopy_visionscience/components/envelopegrating/classic/envelope_grating@2x.png
psychopy_visionscience/components/envelopegrating/classic/envelopegrating.png
psychopy_visionscience/components/envelopegrating/dark/envelopegrating.png
psychopy_visionscience/components/envelopegrating/dark/envelopegrating@2x.png
psychopy_visionscience/components/envelopegrating/light/envelopegrating.png
psychopy_visionscience/components/envelopegrating/light/envelopegrating@2x.png
psychopy_visionscience/components/noise/__init__.py
psychopy_visionscience/components/noise/classic/noise.png
psychopy_visionscience-0.0.7.dist-info/LICENSE
psychopy_visionscience-0.0.7.dist-info/METADATA
psychopy_visionscience-0.0.7.dist-info/WHEEL
psychopy_visionscience-0.0.7.dist-info/entry_points.txt
psychopy_visionscience-0.0.7.dist-info/top_level.txt
psychopy_visionscience-0.0.7.dist-info/RECORD
