Metadata-Version: 2.1
Name: psychopy-visionscience
Version: 0.0.7
Summary: Stimuli useful for vision scientists.
Author: Andrew Schofield
Author-email: Jon Peirce <jon@opensceincetools.org>, Matthew Cutone <mcutone@opensceincetools.org>
License: GNU General Public License v3 (GPLv3)
Project-URL: homepage, https://psychopy.github.io/psychopy-visionscience
Project-URL: changelog, https://github.com/psychopy/psychopy-visionscience/blob/main/CHANGELOG.txt
Project-URL: documentation, https://psychopy.github.io/psychopy-visionscience
Project-URL: repository, https://github.com/psychopy/psychopy-visionscience
Classifier: License :: OSI Approved :: GNU General Public License v3 (GPLv3)
Classifier: Programming Language :: Python :: 3
Classifier: Programming Language :: Python :: 3 :: Only
Classifier: Programming Language :: Python :: 3.7
Classifier: Programming Language :: Python :: 3.8
Classifier: Programming Language :: Python :: 3.9
Classifier: Programming Language :: Python :: 3.10
Classifier: Programming Language :: Python :: 3.11
Classifier: Programming Language :: Python :: Implementation :: CPython
Requires-Python: >=3.7
License-File: LICENSE
Provides-Extra: docs
Requires-Dist: psychopy; extra == "docs"
Requires-Dist: sphinx; extra == "docs"
Requires-Dist: furo; extra == "docs"
Provides-Extra: tests
Requires-Dist: psychopy; extra == "tests"
Requires-Dist: pytest; extra == "tests"
